aiopynamodb/__init__.py
aiopynamodb/_schema.py
aiopynamodb/_util.py
aiopynamodb/attributes.py
aiopynamodb/constants.py
aiopynamodb/exceptions.py
aiopynamodb/indexes.py
aiopynamodb/models.py
aiopynamodb/pagination.py
aiopynamodb/py.typed
aiopynamodb/settings.py
aiopynamodb/signals.py
aiopynamodb/transactions.py
aiopynamodb/types.py
aiopynamodb/connection/__init__.py
aiopynamodb/connection/_aiobotocore_patch.py
aiopynamodb/connection/_botocore_private.py
aiopynamodb/connection/base.py
aiopynamodb/connection/table.py
aiopynamodb/expressions/__init__.py
aiopynamodb/expressions/condition.py
aiopynamodb/expressions/operand.py
aiopynamodb/expressions/projection.py
aiopynamodb/expressions/update.py
aiopynamodb/expressions/util.py
as_aiopynamodb-1.0.1.dist-info/licenses/LICENSE
as_aiopynamodb-1.0.1.dist-info/METADATA
as_aiopynamodb-1.0.1.dist-info/WHEEL
as_aiopynamodb-1.0.1.dist-info/top_level.txt
as_aiopynamodb-1.0.1.dist-info/RECORD
