Metadata-Version: 2.4
Name: as-aiopynamodb
Version: 1.0.1
Summary: An Async Pythonic Interface to DynamoDB
Home-page: http://jlafon.io/pynamodb.html
Author: Jharrod LaFon
Author-email: jlafon@eyesopen.com
License: MIT
Project-URL: Fork, https://github.com/AppSolves/AioPynamoDB
Project-URL: Original, https://github.com/brunobelloni/AioPynamoDB
Keywords: python dynamodb amazon async asyncio aiobotocore
Classifier: Development Status :: 5 - Production/Stable
Classifier: Intended Audience :: Developers
Classifier: Programming Language :: Python
Classifier: Operating System :: OS Independent
Classifier: Programming Language :: Python :: 3.10
Classifier: Programming Language :: Python :: 3.11
Classifier: Programming Language :: Python :: 3.12
Classifier: License :: OSI Approved :: MIT License
Requires-Python: >=3.10
License-File: LICENSE
Requires-Dist: aiobotocore>=2.24.1
Requires-Dist: typing-extensions>=4; python_version < "3.11"
Provides-Extra: signals
Requires-Dist: blinker<2.0,>=1.3; extra == "signals"
Dynamic: author
Dynamic: author-email
Dynamic: classifier
Dynamic: description
Dynamic: description-content-type
Dynamic: home-page
Dynamic: keywords
Dynamic: license
Dynamic: license-file
Dynamic: project-url
Dynamic: provides-extra
Dynamic: requires-dist
Dynamic: requires-python
Dynamic: summary
